pipdownload/__init__.py
pipdownload/__main__.py
pipdownload/cli.py
pipdownload/exceptions.py
pipdownload/settings.py
pipdownload/utils.py
tests/__init__.py
tests/conftest.py
tests/test_cli.py
tests/test_utils.py
aviv_pip_download-0.4.0.post0.dist-info/LICENSE-MIT
aviv_pip_download-0.4.0.post0.dist-info/METADATA
aviv_pip_download-0.4.0.post0.dist-info/WHEEL
aviv_pip_download-0.4.0.post0.dist-info/entry_points.txt
aviv_pip_download-0.4.0.post0.dist-info/top_level.txt
aviv_pip_download-0.4.0.post0.dist-info/RECORD
