Metadata-Version: 2.1
Name: aviv-pip-download
Version: 0.4.0.post0
Summary: A wrapper for pip download in offline scenario.
Home-page: https://github.com/avivabramovich/pip-download
Author: avivabramovich
Author-email: avivabramovich@gmail.com
Maintainer: avivabramovich
Maintainer-email: avivabramovich@gmail.com
License: MIT/Apache-2.0
Keywords: pip download,cross platform,offline packages
Platform: UNKNOWN
Requires-Dist: click
Requires-Dist: requests
Requires-Dist: cachecontrol
Requires-Dist: packaging
Requires-Dist: retrying
Requires-Dist: pip-api
Requires-Dist: tzlocal
Requires-Dist: pip
Requires-Dist: pathlib
Requires-Dist: appdirs
Provides-Extra: dev
Requires-Dist: isort ; extra == 'dev'
Requires-Dist: autoflake ; extra == 'dev'
Requires-Dist: black ; extra == 'dev'
